hasan/__init__.py
hasan/cli.py
hasan/core.py
hasan/vcf_to_tsv.py
hasan-0.2.2.dist-info/METADATA
hasan-0.2.2.dist-info/WHEEL
hasan-0.2.2.dist-info/entry_points.txt
hasan-0.2.2.dist-info/top_level.txt
hasan-0.2.2.dist-info/RECORD
