Metadata-Version: 2.1
Name: hasan
Version: 0.2.2
Summary: A package for haplotype analysis from BAM files
Home-page: https://github.com/yourusername/hasan
Author: SemiQuant
Author-email: Jason.Limberis@ucsf.edu
Classifier: Programming Language :: Python :: 3
Classifier: License :: OSI Approved :: MIT License
Classifier: Operating System :: OS Independent
Requires-Python: >=3.7
Requires-Dist: pysam
Requires-Dist: pandas
Requires-Dist: networkx
Requires-Dist: matplotlib
Requires-Dist: click
Requires-Dist: rich
